{
  "john grisham": "american",
  "dean r. koontz": "american",
  "stephen king": "american",
  "leo tolstoy": "russian",
  "oscar wilde": "irish",
  "james a. michener": "american",
  "roald dahl": "british",
  "peter straub": "american",
  "dale carnegie": "american",
  "james patterson": "american",
  "paul auster": "american",
  "dan brown": "american",
  "lewis carroll": "english",
  "amy tan": "american",
  "e. b. white": "american",
  "neil gaiman": "english",
  "harper lee": "american",
  "michael crichton": "american",
  "nancy taylor rosenberg": "american",
  "dinah mccall": "american",
  "mary higgins clark": "american",
  "friedrich duerenmatt": "swiss",
  "joanne greenberg": "american",
  "augusten burroughs": "american",
  "dennis lehane": "american",
  "albert  camus": "french",
  "chuck palahniuk": "american",
  "thomas harris": "american",
  "robin mckinley": "american",
  "azar nafisi": "iranian-american",
  "kurt vonnegut": "american",
  "richard matheson": "american",
  "ray bradbury": "american",
  "david baldacci": "american",
  "david simon": "american",
  "ken follett": "british",
  "anne tyler": "american",
  "jimmy buffett": "american",
  "tom robbins": "american",
  "pat conroy": "american",
  "isabel allende": "chilean-american",
  "mercedes lackey": "american",
  "dr. seuss": "american",
  "dai sijie": "chinese-french",
  "carol shields": "canadian",
  "tracy chevalier": "american-british",
  "robert anton wilson": "american",
  "gregory maguire": "american",
  "yann martel": "canadian",
  "graham greene": "english",
  "jean rhys": "dominican-born british",
  "nicholas sparks": "american",
  "m. m kaye": "british",
  "laurence": "unknown",
  "betty smith": "american",
  "frances hodgson burnett": "british-american",
  "sue monk kidd": "american",
  "joan d. vinge": "american",
  "david sedaris": "american",
  "trevanian": "american",
  "john irving": "american",
  "mark z. danielewski": "american",
  "jon krakauer": "american",
  "daphne du maurier": "british",
  "s. e. hinton": "american",
  "nathaniel hawthorne": "american",
  "may mcgoldrick": "unknown",
  "david guterson": "american",
  "umberto eco": "italian",
  "marian keyes": "irish",
  "maya angelou": "american",
  "ken kesey": "american",
  "ernest hemingway": "american",
  "sandra brown": "american",
  "dave eggers": "american",
  "arthur golden": "american",
  "bill bryson": "american-british",
  "alice sebold": "american",
  "anna quindlen": "american",
  "toni morrison": "american",
  "frank mccourt": "irish-american",
  "thomas j. stanley": "american",
  "joseph heller": "american",
  "natalie babbitt": "american",
  "scott o'dell": "american",
  "greg iles": "american",
  "j. patrick law": "unknown",
  "richard ford": "american",
  "nick hornby": "english",
  "michael connelly": "american",
  "andre dubus iii": "american",
  "joanne harris": "british",
  "tess gerritsen": "american",
  "orson scott card": "american",
  "w. somerset maugham": "british",
  "george orwell": "british",
  "william sleator": "american",
  "anita shreve": "american",
  "woody allen": "american",
  "sidney sheldon": "american",
  "erich segal": "american",
  "marlo morgan": "american",
  "richard adams": "british",
  "carl hiaasen": "american",
  "e.m. forster": "british",
  "jhumpa lahiri": "british-american",
  "sandra cisneros": "american",
  "jodi picoult": "american",
  "diana gabaldon": "american-scottish",
  "joann ross": "american",
  "glen gold": "unknown",
  "derek hansen": "american",
  "john whitman": "unknown",
  "margaret wise brown": "american",
  "stanislaw lem": "polish",
  "robert heinlein": "american",
  "bertrice small": "american",
  "margaret mitchell": "american",
  "r. jeffers": "american",
  "norton juster": "american",
  "william k. durr": "unknown",
  "alice hoffman": "american",
  "william goldman": "american",
  "david morrell": "canadian-american",
  "d. h. lawrence": "english",
  "hermann hesse": "german-swiss",
  "kate chopin": "american",
  "john steinbeck": "american",
  "john knowles": "american",
  "john saul": "american",
  "phillip margolin": "american",
  "martin walsh": "unknown",
  "jack london": "american",
  "robert louis stevenson": "scottish",
  "judy blume": "american",
  "alice walker": "american",
  "jung chang": "chinese-british",
  "albert camus": "french",
  "john bunyan": "english",
  "michael mc clure": "american",
  "mark twain": "american",
  "nancy kress": "american",
  "marie bourdon": "unknown",
  "bobbi smith": "american",
  "kim newman": "british",
  "h. g. wells": "english",
  "james redfield": "american",
  "beatrix potter": "british",
  "lynsay sands": "canadian",
  "iain pears": "english",
  "l.m. montgomery": "canadian",
  "robert pirsig": "american",
  "agatha christie": "british",
  "joyce carol oates": "american",
  "virginia woolf": "british",
  "sheri s. tepper": "american",
  "joyce reardon": "unknown",
  "frances h. burnett": "british-american",
  "aldous huxley": "british",
  "frank e. peretti": "american",
  "jane austen": "british",
  "robert penn warren": "american",
  "larry mcmurtry": "american",
  "niccolo machiavelli": "italian",
  "michael ondaatje": "sri lankan-canadian",
  "gabriel garcia marquez": "colombian",
  "jane hamilton": "american",
  "john kennedy toole": "american",
  "georgette heyer": "british",
  "george saunders": "american",
  "annie leibovitz": "american",
  "mario puzo": "american",
  "kenneth t. brown": "unknown",
  "ann patchett": "american",
  "charlotte bronte": "british",
  "john g. neihardt": "american",
  "barbara ehrenreich": "american",
  "ted dekker": "american",
  "anne lamott": "american",
  "james mcbride": "american",
  "eric schlosser": "american",
  "monica furlong": "british",
  "anna sewell": "british",
  "ian mcewan": "british",
  "chaim potok": "american",
  "audrey niffenegger": "american",
  "emma donoghue": "irish-canadian",
  "rachel roberts": "unknown",
  "emily bronte": "british",
  "milan kundera": "czech",
  "frances hodgson  burnett": "british-american",
  "zadie smith": "british",
  "ralph ellison": "american",
  "carl sagan": "american",
  "katherine paterson": "american",
  "elspeth joscelin grant huxley": "kenyan-british",
  "tony hawks": "english",
  "anne morrow lindbergh": "american",
  "e. m forster": "british",
  "marilynn robinson": "american",
  "arthur miller": "american",
  "gustave flaubert": "french",
  "john hersey": "american",
  "melinda haynes": "american",
  "charles bukowski": "american",
  "michael moorcock": "english",
  "kahlil gibran": "lebanese-american",
  "jane hissey": "british",
  "salman rushdie": "indian-british",
  "steve martin": "american",
  "arturo perez-reverte": "spanish",
  "saul bellow": "american",
  "j.r.r. tolkien": "english",
  "jonathan harr": "american",
  "kim stanley robinson": "american",
  "richard george adams": "british",
  "philip kindred dick": "american",
  "dodie smith": "english",
  "c. s. lewis": "british",
  "max frisch": "swiss",
  "leon uris": "american",
  "belva plain": "american",
  "barbara kingsolver": "american",
  "joe simpson": "british",
  "geraldine brooks": "australian-american",
  "wilkie collins": "british",
  "isaac bashevis singer": "polish-american",
  "michael chabon": "american",
  "jeanette winterson": "british",
  "neal stephenson": "american",
  "jayne castle": "american",
  "j. d. robb": "american",
  "phoebe conn": "unknown",
  "frank peretti": "american",
  "michael shaara": "american",
  "sarah louise delany": "american",
  "sinclair lewis": "american",
  "charles wheelan": "american",
  "steven pinker": "canadian-american",
  "jostein gaarder": "norwegian",
  "viktor e. frankl": "austrian",
  "paulo coelho": "brazilian",
  "richard bach": "american",
  "shel silverstein": "american",
  "louisa may alcott": "american",
  "pablo neruda": "chilean",
  "katherine neville": "american",
  "madeena s. nolan": "unknown",
  "carlos castaneda": "american",
  "roger zelazny": "american",
  "raymond e. feist": "american",
  "bram stoker": "irish",
  "ian caldwell": "american",
  "robert nye": "british",
  "burton raffel": "american",
  "mary rinehart": "american",
  "jane smiley": "american",
  "connie willis": "american",
  "william s. burroughs": "american",
  "j. r. r. tolkien": "english",
  "kazuo ishiguro": "british",
  "daniel keyes": "american",
  "billy graham": "american",
  "kaye gibbons": "american",
  "oscar hijuelos": "american",
  "douglas coupland": "canadian",
  "philip k. dick": "american",
  "tom stoppard": "british-czech",
  "annie proulx": "american",
  "rohinton mistry": "indian-canadian",
  "carlos ruiz zafon": "spanish",
  "lalita tademy": "american",
  "flannery o'connor": "american",
  "sylvia plath": "american",
  "shusaku endo": "japanese",
  "erich maria remarque": "german",
  "j. m. coetzee": "south african-australian",
  "nathaniel philbrick": "american",
  "sir arthur conan doyle": "british",
  "anthony burgess": "british",
  "f. scott fitzgerald": "american",
  "erich fromm": "german-american",
  "sharon creech": "american",
  "francesca lia block": "american",
  "ann rinaldi": "american",
  "gore vidal": "american",
  "mark dunn": "american",
  "anne sexton": "american",
  "francine hughes": "unknown",
  "ruth l. ozeki": "american-canadian",
  "ann rule": "american",
  "robin maxwell": "american",
  "jane green": "british",
  "louisa m. atcott": "american",
  "nora roberts": "american",
  "j.a. jance": "american",
  "dick francis": "british",
  "malcolm gladwell": "canadian",
  "peter singer": "australian-american",
  "edith wharton": "american",
  "mikhail bulgakov": "russian",
  "gabriel garcã­a mã¡rquez": "colombian",
  "wally lamb": "american",
  "edith nesbit": "british",
  "michel tournier": "french",
  "vladimir nabokov": "russian",
  "gary paulsen": "american",
  "j. d. salinger": "american",
  "william carlos williams": "american",
  "walter kirn": "american",
  "alex garland": "british",
  "russell banks": "american",
  "jack kerouac": "american",
  "jonathan franzen": "american",
  "elizabeth berg": "american",
  "walker percy": "american",
  "eduardo h. galeano": "uruguayan",
  "patrick suskind": "german",
  "micah sparks": "unknown",
  "e m cioran": "romanian-french",
  "toni goffe": "british",
  "lorrie moore": "american",
  "piers anthony": "british-american",
  "lisa carey": "american",
  "julian barnes": "british",
  "legs mcneil": "american",
  "francine prose": "american",
  "t. jefferson parker": "american",
  "antoine de saint-exupã©ry": "french",
  "parris a. bonds": "american",
  "john eldredge": "american",
  "nat philbrick": "american",
  "irvine welsh": "scottish",
  "melanie rawn": "american",
  "e. m. forster": "british",
  "eckhart tolle": "german-canadian",
  "philip roth": "american",
  "minette walters": "british",
  "franz kafka": "austrian-czech",
  "robert mccammon": "american",
  "john updike": "american",
  "mary wollstonecraft shelley": "british",
  "napoleon hill": "american",
  "bret easton ellis": "american",
  "adam gopnik": "canadian-american",
  "christopher moore": "american",
  "murasaki shikibu": "japanese",
  "philippa gregory": "british",
  "tad williams": "american",
  "lorna landvik": "american",
  "peter s. beagle": "american",
  "isaac asimov": "american",
  "wallace earle stegner": "american",
  "mark kurlansky": "american",
  "astrid lindgren": "swedish",
  "james scott bell": "american",
  "ruth reichl": "american",
  "matthew kneale": "british",
  "alice munro": "canadian",
  "e. l. doctorow": "american",
  "martin amis": "british",
  "elizabeth lowell": "american",
  "james joyce": "irish",
  "daniel defoe": "british",
  "stephen r. covey": "american",
  "jayne ann krentz": "american",
  "slavomir rawicz": "polish",
  "marilynne robinson": "american",
  "miguel de cervantes saavedra": "spanish",
  "mark baker": "unknown",
  "hannah alexander": "unknown",
  "jeffrey konvitz": "american",
  "robert r. mccammon": "american",
  "t. j. macgregor": "unknown",
  "richard laymon": "american",
  "iris murdoch": "british-irish",
  "joy kogawa": "canadian",
  "m. bulgakov": "russian",
  "steven paul martini": "unknown",
  "karen harper": "american",
  "jessica mitford": "british",
  "frances burnett": "british-american",
  "truddi chase": "american",
  "frank lauria": "unknown",
  "paul bowles": "american",
  "colin forbes": "british",
  "mandalyn kaye": "unknown",
  "t. coraghessan boyle": "american",
  "billie letts": "american",
  "robert amoroso": "unknown",
  "jules verne": "french",
  "j. r. r tolkien": "english",
  "louis de bernieres": "british",
  "zelig pliskin": "american-israeli",
  "bette greene": "american",
  "dan simmons": "american",
  "john miller": "unknown",
  "sanjay sonawani": "indian",
  "sarah dunant": "british",
  "anthony bourdain": "american",
  "kirill bulychev": "russian",
  "robert b. parker": "american",
  "dava sobel": "american",
  "russell hoban": "american-british",
  "harry mulisch": "dutch",
  "r. f. laird": "unknown",
  "ron chernow": "american",
  "carol saline": "american",
  "henry miller": "american",
  "astrid ericsson lindgren": "swedish",
  "jean little": "canadian",
  "e. nesbit": "british",
  "italo calvino": "italian",
  "ina may gaskin": "american",
  "bentley little": "american",
  "richard bachman": "american",
  "laura esquivel": "mexican",
  "vã­ctor e. villaseã±or": "unknown",
  "melinda metz": "american",
  "pyotyr kurtinski": "unknown",
  "albert einstein": "german-american",
  "doug stanton": "american",
  "zora neale hurston": "american",
  "william w. johnstone": "american",
  "susan wilson": "american",
  "william wood": "unknown",
  "asne seierstad": "norwegian",
  "douglas stone": "unknown",
  "wallace stegner": "american",
  "larry bond": "american",
  "gillian mears": "australian",
  "noah gordon": "american",
  "carson mccullers": "american",
  "calvino italo": "italian",
  "diana silber": "unknown",
  "max barry": "australian",
  "michael cunningham": "american",
  "colson whitehead": "american",
  "stuart woods": "american",
  "anne michaels": "canadian",
  "ann-marie macdonald": "canadian",
  "vladimir vladimirovich nabokov": "russian",
  "susanna tamaro": "italian",
  "amanda quick": "american",
  "roddy doyle": "irish",
  "m. jerry weiss": "american",
  "sigmund freud": "austrian",
  "anne rampling": "american",
  "p. d. james": "british",
  "jill mcgown": "british",
  "edward albee": "american",
  "iyanla vanzant": "american",
  "colum mccann": "irish",
  "bruce ducker": "american",
  "james herbert": "british",
  "peg kerr": "american",
  "gavin menzies": "british",
  "christopher buckley": "american",
  "lawrence m. krauss": "american-canadian",
  "robert fagles": "american",
  "jerome k. jerome": "british",
  "rosamunde pilcher": "british",
  "nichols": "unknown",
  "heller": "unknown",
  "nevil shute": "british",
  "arthur conan, sir doyle": "british",
  "luke davies": "australian",
  "joseph j. ellis": "american",
  "norman mailer": "american",
  "joseph campbell": "american",
  "sophie kinsella": "british",
  "robert k. massie": "american",
  "steve tesich": "serbian-american",
  "edmund morris": "south african-american",
  "nancy milford": "american",
  "william faulkner": "american",
  "rachel carson": "american",
  "tom perrotta": "american",
  "karen joy fowler": "american",
  "john fowles": "british",
  "rick moody": "american",
  "sherman alexie": "american",
  "james a michener": "american",
  "jennings m. burch": "american",
  "fay nedra zachary": "unknown",
  "andy mcnab": "british",
  "tom wolfe": "american",
  "john ashbery": "american",
  "hanif kureishi": "british",
  "judith michael": "american",
  "sir thomas more": "english",
  "judith mcnaught": "american",
  "p. j. o'rourke": "american",
  "noel streatfeild": "british",
  "lynn hall": "american",
  "david mccullough": "american",
  "elisabeth kubler-ross": "swiss-american",
  "don delillo": "american",
  "sarah vowell": "american",
  "cory doctorow": "canadian-british",
  "betty greene": "unknown",
  "ruthanne lum mccunn": "american-chinese",
  "knut hamsun": "norwegian",
  "lowell a. siff": "unknown",
  "lorraine murphy": "unknown",
  "philip dick": "american",
  "randy alcorn": "american",
  "c. s. friedman": "american",
  "marlen haushofer": "austrian",
  "e m forster": "british",
  "anchee min": "chinese-american",
  "sten nadolny": "german",
  "j. m. barrie": "scottish",
  "edward p. jones": "american",
  "ernest j. gaines": "american",
  "terry jones": "british",
  "francis": "unknown",
  "dante alighieri": "italian",
  "ronald f. bridges": "unknown",
  "sophokles": "ancient greek",
  "doris lessing": "british-zimbabwean",
  "edmond rostand": "french",
  "bill clinton": "american",
  "oliver w. sacks": "british",
  "pat booth": "british",
  "peter benchley": "american",
  "robert p. mccammon": "american",
  "brauna e. pouns": "unknown",
  "anita desai": "indian",
  "amelia atwater-rhodes": "american",
  "duerrenmatt": "swiss",
  "malcolm lowry": "british",
  "richard ellmann": "american",
  "patricia maclachlan": "american",
  "wilson rawls": "american",
  "michael ende": "german",
  "alexandre dumas": "french",
  "johanna lindsey": "american",
  "jim hougan": "unknown",
  "john t. lescroart": "american",
  "david james duncan": "american",
  "richard phillips feynman": "american",
  "shannon drake": "american",
  "jonathan kozol": "american",
  "marilyn robinson": "american",
  "m. borroff": "american",
  "sebastien japrisot": "french",
  "david r. morrell": "canadian-american",
  "william thackeray": "british",
  "tobias wolff": "american",
  "george s. clason": "american",
  "steve jackson": "american",
  "joy fielding": "canadian",
  "david lindsey": "american",
  "john treadwell nichols": "american",
  "robert westbrook": "american",
  "sam shepard": "american",
  "elizabeth gilbert": "american",
  "upton beall sinclair": "american",
  "george r. r. martin": "american",
  "eugene gladstone o'neill": "american",
  "desmond morris": "british",
  "patricia highsmith": "american",
  "thomas hardy": "british",
  "not applicable (na )": "unknown",
  "james m cain": "american",
  "david mitchell": "british",
  "peter carey": "australian",
  "oliver sacks": "british",
  "barbara w. tuchman": "american",
  "j.m. coetzee": "south african-australian",
  "lincoln child": "american",
  "jamie grant": "unknown",
  "donald j. trump": "american",
  "fred saberhagen": "american",
  "mary elizabeth murphy": "unknown",
  "richard wright": "american",
  "aristophanes": "ancient greek",
  "howard fast": "american",
  "black elk": "native american",
  "ed mcbain": "american",
  "truman capote": "american",
  "kelli m. gary": "unknown",
  "karel capek": "czech",
  "harold bloom": "american",
  "c potok": "unknown",
  "betty mahmoody": "american",
  "herbert george wells": "english",
  "william  faulkner": "american",
  "lois lenski": "american",
  "lucasarts entertainment company": "unknown",
  "nicole jordan": "american",
  "tabitha king": "american",
  "ul de rico": "italian",
  "p.d. james": "british",
  "michael cecilione": "unknown",
  "douglas clegg": "american",
  "audrey penn": "american",
  "pamela morsi": "american",
  "david gutterson": "american",
  "jack higgins": "british",
  "christopher pike": "american",
  "constance o'day-flannery": "american",
  "kimberly rangel": "unknown",
  "jonathan lethem": "american",
  "francine pascal": "american",
  "katharine stall": "unknown",
  "william golding": "british",
  "michaels": "unknown",
  "shaun hutson": "british",
  "melvin jules bukiet": "american",
  "michael dibdin": "british",
  "zilpha keatley snyder": "american",
  "d.h. lawrence": "british",
  "norman maclean": "american",
  "paul-loup sulitzer": "french",
  "lynda la plante": "british",
  "patricia kay": "american",
  "s. w. hawking": "british",
  "witold gombrowicz": "polish",
  "karl marx": "german",
  "haven kimmel": "american",
  "mary mccarthy": "american",
  "tim obrien": "american",
  "maureen wartski": "american",
  "james hilton": "british",
  "jeffrey m. shaara": "american",
  "p. j. parrish": "american",
  "jonathan  swift": "irish",
  "simon singh": "british",
  "v.s. naipaul": "trinidadian-british",
  "jessica hagedorn": "filipino-american",
  "peter james": "british",
  "william gaddis": "american",
  "pierre boulle": "french",
  "junichiro tanizaki": "japanese",
  "poppy z. brite": "american",
  "antony beevor": "british",
  "barbara samuel": "american",
  "beverly lewis": "american",
  "john mcphee": "american",
  "j. berendt": "american",
  "john cheever": "american",
  "fyodor dostoevsky": "russian",
  "a. c. weisbecker": "american",
  "charles darwin": "british",
  "george eliot": "british",
  "thich nhat hahn": "vietnamese",
  "k. patchen": "unknown",
  "william m. valtos": "unknown",
  "walter dean myers": "american",
  "mike resnick": "american",
  "ken goddard": "unknown",
  "jay r. bonansinga": "american",
  "bernard malamud": "american",
  "laurence yep": "american",
  "m.j. carr": "unknown",
  "eoin colfer": "irish",
  "arwen elys dayton": "american",
  "maurice sendak": "american",
  "mary lavin": "irish",
  "malcolm knox": "australian",
  "rita dove": "american",
  "nikki giovanni": "american",
  "edgar allen poe": "american",
  "mouse works": "unknown",
  "johanna brownnell": "unknown",
  "marilyn manson": "american",
  "chinua achebe": "nigerian",
  "madeleine brent": "british",
  "henry david thoreau": "american",
  "audrey osofsky": "unknown",
  "elie wiesel": "romanian-american",
  "earl hamner": "american",
  "t. s. eliot": "american-british",
  "christopher hampton": "british",
  "nigella lawson": "british",
  "christopher isherwood": "british-american",
  "voltaire": "french",
  "r.a. foakes": "british",
  "sir walter scott": "scottish",
  "c.s. lewis": "british",
  "jane werner": "american",
  "harold coyle": "american",
  "melville": "unknown",
  "carlos casta?eda": "unknown",
  "alexis de tocqueville": "french",
  "homer": "ancient greek",
  "robert graysmith": "american",
  "primo levi": "italian",
  "lori herter": "unknown",
  "g.m. ford": "american",
  "lorris murail": "unknown",
  "ken mcclure": "scottish",
  "tim wolfe": "american",
  "robert frost": "american",
  "jackie french koller": "american",
  "isak dinesen": "danish",
  "mary rosenblum": "american",
  "noel hynd": "american",
  "arthur koestler": "hungarian-british",
  "sun tzu": "ancient chinese",
  "reynolds price": "american",
  "georgia bockoven": "american",
  "henry james": "british-american",
  "christopher priest": "british",
  "wendy rosnau": "american",
  "elizabeth neff walker": "unknown",
  "marilyn campbell": "american",
  "adam hochschild": "american",
  "rosie thomas": "british",
  "ford madox ford": "british",
  "huck scarry": "unknown",
  "mary roach": "american",
  "p.j. o'rourke": "american",
  "connie brockway": "american",
  "sally fairchild": "unknown",
  "hugh laurie": "british",
  "dyan sheldon": "british",
  "zachary alan fox": "unknown",
  "jane mead": "american",
  "m.l. vennum": "unknown",
  "sunzi": "ancient chinese",
  "amelie nothomb": "belgian",
  "billy collins": "american",
  "kenneth mckenney": "unknown",
  "burt reynolds": "american",
  "antonia fraser": "british",
  "barbara ann kipfer": "american",
  "sid fleischman": "american",
  "bernice rubens": "british",
  "catherine anderson": "american",
  "christiane heggan": "american",
  "mary stewart": "british",
  "kathleen nance": "american",
  "fyodor dostoyevsky": "russian",
  "arthur c. clarke": "british",
  "herman wouk": "american",
  "lori byrd": "unknown",
  "errol lincoln uys": "south african",
  "v. s. ramachandran": "indian-american",
  "ian fleming": "british",
  "ivan sergeevich turgenev": "russian",
  "suzanne forster": "american",
  "john gardner": "american",
  "iain m. banks": "scottish",
  "alcott": "american",
  "lewin joel": "unknown",
  "bryce courtenay": "australian",
  "gertrude stein": "american",
  "daniel jonah goldhagen": "american",
  "mark illis": "british",
  "jacob grimm": "german",
  "patricia mc killip": "american",
  "stephen laws": "british",
  "will ferguson": "canadian",
  "walt disney company": "unknown",
  "caroline b. cooney": "american",
  "stendhal": "french",
  "nancy fisher": "unknown",
  "thaddeus carhart": "american",
  "scott edelman": "american",
  "mary morrissy": "irish",
  "yasunari kawabata": "japanese",
  "avi": "american",
  "mary pope osborne": "american",
  "phyllis reynolds naylor": "american",
  "robert fitzgerald": "american",
  "e. wade davis": "canadian",
  "sherry lewis": "unknown",
  "john farris": "american",
  "jin ha": "unknown",
  "jim carroll": "american",
  "alison weir": "british",
  "ian montgomery": "unknown",
  "nikos kazantzakis": "greek",
  "graham masterton": "british",
  "thomas wolfe": "american",
  "douglas adams": "british",
  "thomas keating": "american",
  "ian rankin": "scottish",
  "john lewis": "unknown",
  "barbara wertheim tuchman": "american",
  "robert m. pirsig": "american",
  "julie bertangna": "british",
  "jack higgns": "unknown",
  "for truddi chase troops": "unknown",
  "marie de stendhal": "unknown",
  "charles colson": "american",
  "diane molleson": "unknown",
  "angela elwell hunt": "american",
  "olga bicos": "unknown",
  "william valtos": "unknown",
  "denis johnson": "american",
  "hilary norman": "british",
  "audrey p. johnson": "unknown",
  "ovid": "ancient roman",
  "jonathan swift": "irish",
  "a.c. cawley": "unknown",
  "euripides": "ancient greek",
  "garry wills": "american",
  "ginna gray": "american",
  "mark haddon": "british",
  "ken roy": "unknown",
  "alfred lord tennyson": "british",
  "giovanni pontiero": "british-italian",
  "apollo trust": "unknown",
  "david l. lindsey": "american",
  "william m. thackeray": "british",
  "julian jaynes": "american",
  "victor e. villasenor": "unknown",
  "john philip cohane": "unknown",
  "fyodor m. dostoevsky": "russian",
  "barry holstun lopez": "american",
  "john nichols": "american",
  "andrew solomon": "american",
  "doris kearns goodwin": "american",
  "elizabeth faucher": "unknown",
  "daniel de foe": "british",
  "emily hutchinson": "unknown",
  "doris may lessing": "british-zimbabwean",
  "rachael l. carson": "american",
  "mary higgins-clark": "american",
  "lurlene mcdaniel": "american",
  "upton sinclair": "american",
  "jean paul sartre": "french",
  "michael herr": "american",
  "marvin albert": "american",
  "jim crace": "british",
  "joan didion": "american",
  "jill mansell": "british",
  "philippa pearce": "british",
  "a. n. roquelaure": "american",
  "daniel goleman": "american",
  "f. a. hayek": "austrian-british",
  "tess uriza holthe": "american",
  "james frey": "american",
  "kenzaburo oã«": "japanese",
  "bruce campbell": "american",
  "arthur s. golden": "american",
  "jeff shaara": "american",
  "donald norman": "american",
  "bob tarte": "american",
  "marilyn harris": "american",
  "joyce meyer": "american",
  "tim krabbe": "dutch",
  "eugene o'neill": "american",
  "sarah dessen": "american",
  "nikolai vasilevich gogol": "russian",
  "pelham grenville wodehouse": "british",
  "erich m remarque": "german",
  "wade davis": "canadian",
  "thomas bulfinch": "american",
  "robert a. caro": "american",
  "p. g. wodehouse": "british",
  "joe farris": "unknown",
  "maxx barry": "australian",
  "john marks": "unknown",
  "stephen hawking": "british",
  "nikolai v. gogol": "russian",
  "alexandra marshall": "unknown",
  "bill eidson": "unknown",
  "le ly hayslip": "vietnamese-american",
  "monica fulong": "unknown",
  "c bronte": "british",
  "charles deemer": "american",
  "tobsha learner": "australian-british",
  "nelson mandela": "south african",
  "random house disney": "unknown",
  "lavinia derwent": "scottish",
  "barbara betcherman": "unknown",
  "carol ellis": "american",
  "david goodis": "american",
  "neal travis": "unknown",
  "h. melville": "unknown",
  "stephen jay gould": "american",
  "william gibson": "american-canadian",
  "naguib mahfouz": "egyptian",
  "jeff long": "american",
  "alexander solzhenitsyn": "russian",
  "bill zehme": "american",
  "golda mier": "israeli",
  "echo heron": "american",
  "frederick phillips brooks": "american",
  "steve mcconnell": "american",
  "jenny carroll": "american",
  "lucy maud montgomery": "canadian",
  "joseph wambaugh": "american",
  "frank o'connor": "american",
  "bell hooks": "american",
  "mary shelley": "british",
  "anne logston": "american",
  "sylvia engdahl": "american",
  "studs terkel": "american",
  "eric schulman": "unknown",
  "v. s. naipaul": "trinidadian-british",
  "cheever": "unknown",
  "betty friedan": "american",
  "penn williamson": "unknown",
  "michael swanwick": "american",
  "kate nevins": "unknown",
  "joseph conrad": "polish-british",
  "harold pinter": "british",
  "beverly barton": "american",
  "kirk douglas": "american",
  "eli cantor": "unknown",
  "walt disney": "american",
  "edwidge danticat": "haitian-american",
  "james bradley": "american",
  "daphnã?â© du maurier": "british",
  "paul theroux": "american",
  "lesley baxter": "unknown",
  "ben, m.d carson": "american",
  "evelyn a. crowe": "unknown",
  "hunter s. thompson": "american",
  "joe. orton": "british",
  "p d james": "british",
  "thich nhat hanh": "vietnamese",
  "celia brayfield": "british",
  "serena carrington": "unknown",
  "p. yogananda": "indian",
  "john barth": "american",
  "john milton": "british",
  "padraic o conaire": "irish",
  "liz curtis higgs": "american",
  "c.f. baynes": "unknown",
  "nicholas christopher": "american",
  "kant": "german",
  "dante": "italian",
  "emile zola": "french",
  "alexis de tocquevil": "unknown",
  "walter scott": "scottish",
  "stephen marlowe": "american",
  "o'dell scott": "unknown",
  "liz rigbey": "unknown",
  "henry fielding": "british",
  "gwendolyn brooks": "american",
  "michael palin": "british",
  "george r.r. martin": "american",
  "tony thorne": "unknown",
  "kathleen winsor": "american",
  "frances nugent": "unknown",
  "joanna wissinger": "american",
  "edmund crispin": "british",
  "david eddings": "american",
  "kerry patterson": "american",
  "henri matisse": "french",
  "erich marie remarque": "german",
  "michael lewis": "american",
  "alan moore": "british",
  "patrick o'leary": "american",
  "philip pullman": "british",
  "l m montgomery": "canadian",
  "steinbeck j": "unknown",
  "eric carle": "american",
  "christopher hitchens": "british-american",
  "bryan forbes": "british",
  "james baldwin": "american",
  "todd solondz": "american",
  "ray monk": "british",
  "a.s. byatt": "british",
  "robert mccloskey": "american",
  "wislawa szymborska": "polish",
  "dashiell hammett": "american",
  "virginia lee burton": "american",
  "howard norman": "american",
  "j d salinger": "american",
  "virgil": "ancient roman",
  "eric hansen": "american",
  "lawrence schimel": "american",
  "steven pressfield": "american",
  "jon lee anderson": "american",
  "tracy lynn": "unknown",
  "claudia crawford": "unknown",
  "golden books": "unknown",
  "robert m. sapolsky": "american",
  "robert irwin": "australian",
  "tamara thorne": "american",
  "sally emerson": "british",
  "bradbury": "unknown",
  "john c. gardner": "unknown",
  "john hodge": "british",
  "walter simonson": "american",
  "emmanouel d. rhoides": "greek",
  "lisa appignanesi": "polish-british",
  "taichi yamada": "japanese",
  "john donne": "british",
  "timothy findley": "canadian",
  "daniel clowes": "american",
  "harris": "unknown",
  "emily giffin": "american",
  "l. m. montgomery": "canadian",
  "thad carhart": "american",
  "philippa carr": "american",
  "jerry pournelle": "american",
  "sebastian faulks": "british",
  "mark salzman": "american",
  "flann o'brien": "irish",
  "jude deveraux": "american",
  "william hjortsberg": "american",
  "e. l. hastings": "unknown",
  "walt disney productions": "unknown",
  "anne stuart": "american",
  "james b. stewart": "american",
  "joseph p. desario": "unknown",
  "r. karl largent": "unknown",
  "luane roche": "unknown",
  "grahame greene": "british",
  "conrad richter": "american",
  "melanie jackson": "unknown",
  "catherine spangler": "american",
  "james jennings": "unknown",
  "daniel c. dennett": "american",
  "humphery carpenter": "british",
  "r. massie": "unknown",
  "david allen": "american",
  "l. n. tolstoi": "russian",
  "gary devon": "unknown",
  "james morrow": "american",
  "eldon grier": "canadian",
  "ralph gustafson": "canadian",
  "doug hornig": "american",
  "ira levin": "american",
  "alice miller": "polish-swiss",
  "helen fielding": "british",
  "steven piziks": "american",
  "kate clemens": "unknown",
  "wendy morgan": "unknown",
  "stoker bram": "unknown",
  "ernest becker": "american",
  "grace paley": "american",
  "iain banks": "scottish",
  "arthur nersesian": "american",
  "david e kaplans": "unknown",
  "james kirkwood": "american",
  "hannah green": "american",
  "oliver w sacks": "british",
  "john ehrlichman": "american",
  "jean simon": "unknown",
  "hannah arendt": "german-american",
  "ben jonson": "british",
  "roland h. bainton": "american",
  "immanuel kant": "german",
  "jean-paul sartre": "french",
  "maureen gallery kovacs": "american",
  "jen mcveity": "australian",
  "sophocles": "ancient greek",
  "jenkins": "unknown",
  "arden": "unknown",
  "stevie smith": "british",
  "aesop": "ancient greek",
  "jenny joseph": "british",
  "alan dugan": "american",
  "sarah delany": "american",
  "ken kalfus": "american",
  "w.g. sebald": "german",
  "kasey michaels": "american",
  "james a. machener": "american",
  "st. augustine": "roman-african",
  "lisa gregory": "american",
  "philip makanna": "american",
  "loung ung": "cambodian-american",
  "martin millar": "scottish",
  "drusilla modjeska": "australian",
  "niccolã² machiavelli": "italian",
  "lori paris": "unknown",
  "stanislav lem": "polish",
  "jeffrey eugenides": "american",
  "w.a. harbinson": "northern irish",
  "v. s naipaul": "trinidadian-british",
  "tom grimes": "american",
  "colm toibin": "irish",
  "reginald hill": "british",
  "michael grant": "american",
  "pierre rey": "french",
  "frank simon": "unknown",
  "alexis  tocqueville": "unknown",
  "joseph l. heller": "american",
  "ishmael reed": "american",
  "andrea dworkin": "american",
  "richard paige": "unknown",
  "william trevor": "irish",
  "thomas cahill": "american",
  "lucy wadham": "british",
  "carl sandburg": "american",
  "robert whitlow": "american",
  "fern michaels": "american",
  "gene wolfe": "american",
  "ursula k. le guin": "american",
  "michael a. smith": "unknown",
  "robert mason": "american",
  "julie otsuka": "american",
  "kate adie": "british",
  "val mcdermid": "scottish",
  "elmore leonard": "american",
  "laurie lawlor": "american",
  "ken englade": "american",
  "john gordon davis": "unknown",
  "joan grant": "british",
  "nancy a. collins": "american",
  "margaret bingley": "british",
  "anita diamant": "american",
  "elena castedo": "spanish-american",
  "gloria naylor": "american",
  "rosemary ellen guiley": "american",
  "steven spielberg": "american",
  "jessica stirling": "british",
  "reinaldo arenas": "cuban",
  "josephine hart": "irish",
  "alan hollinghurst": "british",
  "tom  morris": "unknown",
  "elizabeth george": "american",
  "james m. barrie": "unknown",
  "barbara larriva": "unknown",
  "graham swift": "british",
  "halldor laxness": "icelandic",
  "peter kuper": "american",
  "glen david gold": "american",
  "larry niven": "american",
  "robert steele gray": "unknown",
  "frank d. mcconnell": "american",
  "amin maalouf": "lebanese-french",
  "kristin mccloy": "american",
  "robert westall": "british",
  "j. n. williamson": "american",
  "lev nikalaevich tolstoi": "russian",
  "karen hesse": "american",
  "karyn langhorne": "american",
  "will shetterly": "american",
  "john shirley": "american",
  "peter f. hamilton": "british",
  "david hewson": "british",
  "john altman": "american",
  "posie graeme-evans": "new zealander",
  "joel c. rosenberg": "american",
  "brian stableford": "british",
  "beth saulnier": "american",
  "sharon k. garner": "unknown",
  "justine wittich": "unknown",
  "ha jin": "chinese-american",
  "jefferson carter": "american",
  "friedrich w. nietzsche": "german",
  "miguel de cervantes": "spanish",
  "louis-ferdinand celine": "french",
  "shauna singh baldwin": "canadian",
  "rhiannon lassiter": "british",
  "houghton mifflin company": "unknown",
  "william mcdonough": "american",
  "frank shaw": "unknown",
  "j m barrie": "british",
  "jane rogers": "british",
  "robin lee hatcher": "american",
  "chris van allsburg": "american",
  "m.j. rodgers": "american",
  "thomas sowell": "american",
  "ross leckie": "canadian",
  "william blake": "british",
  "dr seuss": "american",
  "rodney peppe": "british",
  "william manchester": "american",
  "william s burroughs": "american",
  "stella cameron": "british",
  "brian patten": "british",
  "jackie hyman": "american",
  "nicole krauss": "american",
  "morgan scott peck": "american",
  "lindsay chase": "unknown",
  "robert taylor": "unknown",
  "robert greene": "american",
  "anne mclean matthews": "unknown",
  "fydor dostoyevsky": "russian",
  "chaz brenchley": "british",
  "gordon": "unknown",
  "j. a. carruth": "unknown",
  "john mortimer": "british",
  "hans ulrich treichel": "german",
  "manly wade wellman": "american",
  "c. terry cline": "unknown",
  "john coyne": "american",
  "tribute": "unknown",
  "michener a.": "unknown",
  "paul gambaccini": "american-british",
  "saint augustine": "roman-north african",
  "june easton": "unknown",
  "james mccallum": "unknown",
  "frances j. roberts": "american",
  "jonathan nasaw": "american",
  "alexis hart": "unknown",
  "george selden": "american",
  "robin j. gunn": "american",
  "mary w. shelly": "unknown",
  "richard h. minear": "american",
  "tommy lee": "american",
  "giles gordon": "british",
  "steve zettler": "american",
  "william katz": "unknown",
  "karl lassiter": "unknown",
  "karen tei yamashita": "american",
  "arthur herzog": "american",
  "lois greiman": "american",
  "sanyika shakur": "american",
  "cummings": "unknown",
  "mary j. jones": "unknown",
  "patrick m.  lencioni": "american",
  "robert hellenga": "american",
  "will hobbs": "american",
  "muhammad yunus": "bangladeshi",
  "richard sapir": "american",
  "r. kent hughes": "american",
  "nikolai gogol": "russian-ukrainian",
  "robert fulghum": "american",
  "hamilton deane": "irish",
  "friedrich a. hayek": "austrian-british",
  "dan waddell": "british",
  "winston s. churchill": "british",
  "mary roberts rinehart": "american",
  "kurt busiek": "american",
  "richard a. wright": "unknown",
  "lawrence durrell": "british",
  "jane rule": "canadian",
  "meredy maynard": "unknown",
  "norman rush": "american",
  "doris vallejo": "american",
  "patricia jones": "unknown",
  "peter dally": "british",
  "barbara hambly": "american",
  "t.           t gunn": "unknown",
  "terry vance": "unknown",
  "edmond rostland": "french",
  "penny richards": "unknown",
  "maxine o'callaghan": "unknown",
  "galway kinnell": "american",
  "uris": "unknown",
  "anita mills": "american",
  "bil keane": "american",
  "william g. golding": "unknown",
  "jon f. merz": "american",
  "joe orton": "british",
  "john banville": "irish",
  "john r. colombo": "canadian",
  "defoe": "british",
  "j. m. synge": "irish",
  "natsuo kirino": "japanese",
  "wollstonecraft mary shelley": "british",
  "peggy j. herring": "unknown",
  "claire messud": "american",
  "wallace howard": "unknown",
  "trent lynda": "unknown",
  "raymond queneau": "french",
  "christina crawford": "american",
  "aime cesaire": "martiniquan-french",
  "lily brett": "australian",
  "orhan pamuk": "turkish",
  "warren ellis": "british",
  "emmuska orczy": "hungarian-british",
  "glenda finkelstein": "unknown",
  "kevin r. paglia": "unknown",
  "w.s. kuniczak": "american",
  "tom paxton": "american",
  "armand marie leroi": "new zealander",
  "gretchen moran laskas": "american",
  "ryu murakami": "japanese",
  "john kerouac": "american",
  "ludwig wittgenstein": "austrian-british",
  "helen morris": "unknown",
  "robert l stevenson": "unknown",
  "ed koch": "american",
  "jill ciment": "canadian",
  "fritz leiber": "american",
  "steven bauer": "american",
  "margaret olwen macmillan": "canadian",
  "john lutz": "american",
  "thomas h. middleton": "unknown",
  "caryl rivers": "american",
  "robert creeley": "american",
  "joe sacco": "maltese-american",
  "danny p. jackson": "american",
  "frances fyfield": "british",
  "leslie h. whitten": "american",
  "antoinette stockenberg": "american",
  "joan wolf": "american",
  "frederic bean": "unknown",
  "greg hildebrandt": "american",
  "arthur conan doyle": "british",
  "colm mccann": "irish",
  "robert asprin": "american",
  "eva figes": "british",
  "lama foundation editor": "unknown",
  "jennifer taylor": "unknown",
  "eric jerome dickey": "american",
  "antoine de saint exupery": "french",
  "stephanie spinner": "american",
  "howard zinn": "american",
  "jorge a. livraga rizzi": "argentine",
  "fay weldon": "new zealander-british",
  "kathy hill": "unknown",
  "pearl s. buck": "american",
  "fedor mikhailovich, dostoevskii": "russian",
  "paul pitchford": "american",
  "katharine marlowe": "unknown",
  "victoria finlay": "british",
  "burgess": "unknown",
  "sylvia louise engdahl": "american",
  "marc brandel": "unknown",
  "menelaos stephanides": "unknown",
  "thomas harrris": "american",
  "james byron huggins": "american",
  "martin h. greenberg": "american",
  "andrew hunt": "american",
  "norah lofts": "british",
  "plato.": "ancient greek",
  "jenna jameson": "american",
  "dee davis": "american",
  "michael ignatieff": "canadian",
  "j. k. rowling": "british",
  "alighieri dante": "italian",
  "joan aiken": "british",
  "dahl": "unknown",
  "thomas perry": "american",
  "tomas moro": "spanish",
  "terry southern": "american",
  "antonia barber": "british",
  "william poundstone": "american",
  "robert graves": "british",
  "shirley lord": "american",
  "clarissa watson": "unknown",
  "ann mcgovern": "american",
  "robert bloch": "american",
  "ovid demaris": "american",
  "jo walton": "british",
  "adrian plass": "british",
  "hjalmar soderberg": "swedish",
  "rebecca hagan lee": "american",
  "mark a. garland": "unknown",
  "tim kincaid": "american",
  "christopher hart": "unknown",
  "tacitus": "ancient roman",
  "anya seton": "american",
  "james mallahan cain": "american",
  "brian wildsmith": "british",
  "wells": "unknown",
  "theresa breslin": "scottish",
  "terry durack": "australian",
  "aleksandr sergeevich pushkin": "russian",
  "sandra kitt": "american",
  "hugh kenner": "canadian",
  "jonathan kellerman": "american",
  "isadora duncan": "american",
  "helen glisic": "unknown",
  "tim richards": "unknown",
  "mian mian": "chinese",
  "david mcrobbie": "australian",
  "denise levertov": "british-american",
  "daphne dumaurier": "british",
  "nicholas luard": "british",
  "elizabeth fishel": "american",
  "al ries": "american",
  "candy barr": "american",
  "kathryn lasky knight": "american",
  "gabriel garcia-marquez": "colombian",
  "irving jensen": "unknown",
  "thomas mann": "german",
  "kathy acker": "american",
  "nadine gordimer": "south african",
  "james a. baldwin": "american",
  "paramahansa yogananda": "indian",
  "ben, dr bova": "american",
  "bram stocker": "unknown",
  "charlene raddon": "american",
  "cervantes": "spanish",
  "baricco": "italian",
  "geoffrey chaucer": "british",
  "nancy baker jacobs": "unknown",
  "christinia crawford": "unknown",
  "elizabeth cowan, neeld": "unknown",
  "michael d coe": "american",
  "m. e. kerr": "american",
  "madeline baker": "american",
  "nancy morse": "unknown",
  "geert mak": "dutch",
  "raymond carver": "american",
  "max kinnings": "british",
  "dylan thomas": "welsh",
  "elliot perlman": "australian",
  "peter mcwilliams": "american",
  "dallas schulze": "american",
  "audrey reimann": "unknown",
  "najib mahfuz": "unknown",
  "patricia potter": "unknown",
  "nancy tay rosenberg": "unknown",
  "yvonne macmanus": "unknown",
  "myrna grant": "unknown",
  "malcolm lowery": "unknown",
  "randall jarrell": "american",
  "george clason": "american",
  "daniel halpern": "american",
  "quinn currie": "unknown",
  "charles ross": "unknown",
  "john malathronas": "british",
  "malcolm godwin": "british",
  "robet duncan": "unknown",
  "will durant": "american",
  "rachael carson": "american",
  "ronald takaki": "american",
  "david herbert lawrence": "british",
  "teresa moorey": "british",
  "w. h. auden": "british-american",
  "true summers": "unknown",
  "deborah moggach": "british",
  "ellen raskin": "american",
  "steve harris": "unknown",
  "k hamson": "unknown",
  "karen armstrong": "british",
  "marta randall": "american",
  "joyce carol thomas": "american",
  "bruce gamble": "american",
  "gabriel  garcia marquez": "colombian",
  "valerie martin": "american",
  "marguerite duras": "french",
  "joanna traynor": "british",
  "janette turner hospital": "australian",
  "david mcphail": "american",
  "t. lucien wright": "unknown",
  "jonathan green": "british",
  "jerome david salinger": "american",
  "bryan magee": "british",
  "harold robbins": "american",
  "welwyn wilton katz": "canadian",
  "mark childress": "american",
  "shute": "unknown",
  "margot j. fromer": "unknown",
  "m. l. gamble": "unknown",
  "george gipe": "american",
  "erica jong": "american",
  "frank tuohy": "irish",
  "anne bronte": "british",
  "guy dauncey": "british-canadian"
}
